[
    {
        "groupId": "ED46DB32-3288-4DAA-9BD7-0DE380E65EFD",
        "affinityGroup": "Individual",
        "nino": "JT321500D",
        "user": {
            "credId": "5427463575104737",
            "name": "Firstname Surname",
            "email": "email5@test.com",
            "userId": "Ending with 0297",
            "hasPTEnrolment": false
        }
    },
    {
        "groupId": "223F5A44-692B-47D8-9F0B-90A4A8C1597E",
        "affinityGroup": "Individual",
        "nino": "JT321500D",
        "user": {
            "credId": "6872602021135400",
            "name": "Firstname Surname",
            "email": "email7@test.com",
            "userId": "Ending with 1655",
            "hasPTEnrolment": false
        }
    }
]
